newtgw/__init__.py
newtgw/py.typed
newtgw/_jsii/__init__.py
newtgw/_jsii/newtgw@0.0.14.jsii.tgz
newtgw-0.0.14.dist-info/LICENSE
newtgw-0.0.14.dist-info/METADATA
newtgw-0.0.14.dist-info/WHEEL
newtgw-0.0.14.dist-info/top_level.txt
newtgw-0.0.14.dist-info/RECORD
